Androidtrainingchs/README.md
Androidtrainingchs/__init__.py
Androidtrainingchs/__main__.py
Androidtrainingchs/file.epub
Androidtrainingchs/index.html
Androidtrainingchs/css/__init__.py
Androidtrainingchs/css/annotations.css
Androidtrainingchs/css/main.css
Androidtrainingchs/css/normalize.css
Androidtrainingchs/css/popup.css
Androidtrainingchs/font/__init__.py
Androidtrainingchs/font/fontello.eot
Androidtrainingchs/font/fontello.svg
Androidtrainingchs/font/fontello.ttf
Androidtrainingchs/font/fontello.woff
Androidtrainingchs/img/__init__.py
Androidtrainingchs/img/annotator-glyph-sprite.png
Androidtrainingchs/img/annotator-icon-sprite.png
Androidtrainingchs/img/apple-touch-icon.png
Androidtrainingchs/img/cancelfullscreen.png
Androidtrainingchs/img/close.png
Androidtrainingchs/img/fullscreen.png
Androidtrainingchs/img/loader.gif
Androidtrainingchs/img/menu-icon.png
Androidtrainingchs/img/save.png
Androidtrainingchs/img/saved.png
Androidtrainingchs/img/settings-s.png
Androidtrainingchs/img/settings.png
Androidtrainingchs/img/star.png
Androidtrainingchs/js/__init__.py
Androidtrainingchs/js/epub.js
Androidtrainingchs/js/epub.min.js
Androidtrainingchs/js/epub.min.map
Androidtrainingchs/js/hooks.min.js
Androidtrainingchs/js/hooks.min.map
Androidtrainingchs/js/reader.js
Androidtrainingchs/js/reader.js.map
Androidtrainingchs/js/reader.min.js
Androidtrainingchs/js/reader.min.map
Androidtrainingchs/js/hooks/__init__.py
Androidtrainingchs/js/hooks/extensions/__init__.py
Androidtrainingchs/js/hooks/extensions/highlight.js
Androidtrainingchs/js/libs/__init__.py
Androidtrainingchs/js/libs/jquery.min.js
Androidtrainingchs/js/libs/localforage.min.js
Androidtrainingchs/js/libs/screenfull.js
Androidtrainingchs/js/libs/screenfull.min.js
Androidtrainingchs/js/libs/zip.min.js
Androidtrainingchs/js/plugins/__init__.py
Androidtrainingchs/js/plugins/hypothesis.js
Androidtrainingchs/js/plugins/search.js
androidtrainingchs-2024.2.29.0.dist-info/METADATA
androidtrainingchs-2024.2.29.0.dist-info/WHEEL
androidtrainingchs-2024.2.29.0.dist-info/entry_points.txt
androidtrainingchs-2024.2.29.0.dist-info/top_level.txt
androidtrainingchs-2024.2.29.0.dist-info/RECORD
